google/cloud/pubsub/__init__.py
google/cloud/pubsub_v1/__init__.py
google/cloud/pubsub_v1/exceptions.py
google/cloud/pubsub_v1/futures.py
google/cloud/pubsub_v1/types.py
google/cloud/pubsub_v1/open_telemetry/__init__.py
google/cloud/pubsub_v1/open_telemetry/context_propagation.py
google/cloud/pubsub_v1/open_telemetry/publish_message_wrapper.py
google/cloud/pubsub_v1/open_telemetry/subscribe_opentelemetry.py
google/cloud/pubsub_v1/proto/pubsub.proto
google/cloud/pubsub_v1/proto/schema.proto
google/cloud/pubsub_v1/publisher/__init__.py
google/cloud/pubsub_v1/publisher/client.py
google/cloud/pubsub_v1/publisher/exceptions.py
google/cloud/pubsub_v1/publisher/flow_controller.py
google/cloud/pubsub_v1/publisher/futures.py
google/cloud/pubsub_v1/publisher/_batch/__init__.py
google/cloud/pubsub_v1/publisher/_batch/base.py
google/cloud/pubsub_v1/publisher/_batch/thread.py
google/cloud/pubsub_v1/publisher/_sequencer/__init__.py
google/cloud/pubsub_v1/publisher/_sequencer/base.py
google/cloud/pubsub_v1/publisher/_sequencer/ordered_sequencer.py
google/cloud/pubsub_v1/publisher/_sequencer/unordered_sequencer.py
google/cloud/pubsub_v1/subscriber/__init__.py
google/cloud/pubsub_v1/subscriber/client.py
google/cloud/pubsub_v1/subscriber/exceptions.py
google/cloud/pubsub_v1/subscriber/futures.py
google/cloud/pubsub_v1/subscriber/message.py
google/cloud/pubsub_v1/subscriber/scheduler.py
google/cloud/pubsub_v1/subscriber/_protocol/__init__.py
google/cloud/pubsub_v1/subscriber/_protocol/dispatcher.py
google/cloud/pubsub_v1/subscriber/_protocol/heartbeater.py
google/cloud/pubsub_v1/subscriber/_protocol/helper_threads.py
google/cloud/pubsub_v1/subscriber/_protocol/histogram.py
google/cloud/pubsub_v1/subscriber/_protocol/leaser.py
google/cloud/pubsub_v1/subscriber/_protocol/messages_on_hold.py
google/cloud/pubsub_v1/subscriber/_protocol/requests.py
google/cloud/pubsub_v1/subscriber/_protocol/streaming_pull_manager.py
google/pubsub/__init__.py
google/pubsub/gapic_version.py
google_cloud_pubsub-2.29.0.dist-info/LICENSE
google_cloud_pubsub-2.29.0.dist-info/METADATA
google_cloud_pubsub-2.29.0.dist-info/WHEEL
google_cloud_pubsub-2.29.0.dist-info/top_level.txt
google_cloud_pubsub-2.29.0.dist-info/RECORD
