Metadata-Version: 2.1
Name: google-cloud-pubsub
Version: 2.29.0
Summary: Google Cloud Pub/Sub API client library
Home-page: https://github.com/googleapis/python-pubsub
Author: Google LLC
Author-email: googleapis-packages@google.com
License: Apache 2.0
Platform: Posix; MacOS X; Windows
Classifier: Development Status :: 5 - Production/Stable
Classifier: Intended Audience :: Developers
Classifier: License :: OSI Approved :: Apache Software License
Classifier: Programming Language :: Python
Classifier: Programming Language :: Python :: 3
Classifier: Programming Language :: Python :: 3.7
Classifier: Programming Language :: Python :: 3.8
Classifier: Programming Language :: Python :: 3.9
Classifier: Programming Language :: Python :: 3.10
Classifier: Programming Language :: Python :: 3.11
Classifier: Programming Language :: Python :: 3.12
Classifier: Programming Language :: Python :: 3.13
Classifier: Operating System :: OS Independent
Classifier: Topic :: Internet
Requires-Python: >=3.7
License-File: LICENSE
Requires-Dist: grpcio<2.0.0,>=1.51.3
Requires-Dist: google-auth<3.0.0,>=2.14.1
Requires-Dist: google-api-core[grpc]!=2.0.*,!=2.1.*,!=2.10.*,!=2.2.*,!=2.3.*,!=2.4.*,!=2.5.*,!=2.6.*,!=2.7.*,!=2.8.*,!=2.9.*,<3.0.0,>=1.34.0
Requires-Dist: proto-plus<2.0.0,>=1.22.0
Requires-Dist: proto-plus<2.0.0,>=1.22.2; python_version >= "3.11"
Requires-Dist: proto-plus<2.0.0,>=1.25.0; python_version >= "3.13"
Requires-Dist: protobuf!=4.21.0,!=4.21.1,!=4.21.2,!=4.21.3,!=4.21.4,!=4.21.5,<7.0.0,>=3.20.2
Requires-Dist: grpc-google-iam-v1<1.0.0,>=0.12.4
Requires-Dist: grpcio-status>=1.33.2
Requires-Dist: opentelemetry-api<=1.22.0; python_version <= "3.7"
Requires-Dist: opentelemetry-api>=1.27.0; python_version >= "3.8"
Requires-Dist: opentelemetry-sdk<=1.22.0; python_version <= "3.7"
Requires-Dist: opentelemetry-sdk>=1.27.0; python_version >= "3.8"
Provides-Extra: libcst
Requires-Dist: libcst>=0.3.10; extra == "libcst"
